{
    "category": [
        {
            "categoryId": 1,
            "categoryName": "Cà phê nóng",
            "items": [
                {
                    "id": 1,
                    "name": "Americano",
                    "description": "",
                    "imgUrl": "https://mcdonalds.vn/uploads/2018/mccafe/xamericano.png.pagespeed.ic.7cM8I0KdtJ.webp",
                    "size": [
                        {
                            "sizeName": "M",
                            "price": 39000
                        },
                        {
                            "sizeName": "L",
                            "price": 59000
                        }
                    ]
                },
                {
                    "id": 2,
                    "name": "Cappuccino",
                    "description": "",
                    "imgUrl": "https://mcdonalds.vn/uploads/2018/mccafe/xcappucino.png.pagespeed.ic.k1IWeRdO94.webp",
                    "size": [
                        {
                            "sizeName": "M",
                            "price": 49000
                        },
                        {
                            "sizeName": "L",
                            "price": 79000
                        }
                    ]
                },
                {
                    "id": 3,
                    "name": "Matcha Latte Nóng",
                    "description": "",
                    "imgUrl": "https://mcdonalds.vn/uploads/2018/mccafe/xhotmatcha.png.pagespeed.ic.i1Eo-BIuI3.webp",
                    "size": [
                        {
                            "sizeName": "M",
                            "price": 60000
                        },
                        {
                            "sizeName": "L",
                            "price": 90000
                        }
                    ]
                },
                {
                    "id": 4,
                    "name": "Sô cô la nóng",
                    "description": "",
                    "imgUrl": "https://mcdonalds.vn/uploads/2018/mccafe/xhotchoco.png.pagespeed.ic.JeBzsBa6Hl.webp",
                    "size": [
                        {
                            "sizeName": "M",
                            "price": 49000 
                        },
                        {
                            "sizeName": "L",
                            "price": 70000
                        }
                    ]
                },
                {
                    "id": 5,
                    "name": "Latte nóng",
                    "description": "",
                    "imgUrl": "https://mcdonalds.vn/uploads/2018/mccafe/xhotlatte.png.pagespeed.ic.R7x0I_O1_4.webp",
                    "size": [
                        {
                            "sizeName": "M",
                            "price": 49000 
                        },
                        {
                            "sizeName": "L",
                            "price": 70000
                        }
                    ]
                },
                {
                    "id": 6,
                    "name": "Cà phê Mocha",
                    "description": "",
                    "imgUrl": "https://mcdonalds.vn/uploads/2018/mccafe/xmocha.png.pagespeed.ic.ojvyB7tqPu.webp",
                    "size": [
                        {
                            "sizeName": "M",
                            "price": 59000 
                        },
                        {
                            "sizeName": "L",
                            "price": 79000
                        }
                    ]
                }
            ]
        },
        {
            "categoryId": 2,
            "categoryName": "Cà phê đá",
            "item": [
                {
                    "id": 1,
                    "name": "Cà phê sữa đá Việt Nam",
                    "description": "",
                    "imgUrl": "https://mcdonalds.vn/uploads/2018/mccafe/xiced_milkVNcoffee.png.pagespeed.ic.c95-PmcQXX.webp",
                    "size": [
                        {
                            "sizeName": "M",
                            "price": 35000 
                        },
                        {
                            "sizeName": "L",
                            "price": 49000
                        }
                    ]
                },
                {
                    "id": 2,
                    "name": "Cà phê Americano đá",
                    "description": "",
                    "imgUrl": "https://mcdonalds.vn/uploads/2018/mccafe/xicedamericano.png.pagespeed.ic.vblLTd6fO3.webp",
                    "size": [
                        {
                            "sizeName": "M",
                            "price": 45000 
                        },
                        {
                            "sizeName": "L",
                            "price": 65000
                        }
                    ]
                },
                {
                    "id": 3,
                    "name": "Cà phê Latte đá",
                    "description": "",
                    "imgUrl": "https://mcdonalds.vn/uploads/2018/mccafe/xicedlatte.png.pagespeed.ic.uALe6PqshS.webp",
                    "size": [
                        {
                            "sizeName": "M",
                            "price": 55000 
                        },
                        {
                            "sizeName": "L",
                            "price": 69000
                        }
                    ]
                },
                {
                    "id": 4,
                    "name": "Cà phê đen đá Việt Nam",
                    "description": "",
                    "imgUrl": "https://mcdonalds.vn/uploads/2018/mccafe/xiced_VNcoffee.png.pagespeed.ic.pVzI8nKPCq.webp",
                    "size": [
                        {
                            "sizeName": "M",
                            "price": 35000 
                        },
                        {
                            "sizeName": "L",
                            "price": 59000
                        }
                    ]
                },
                {
                    "id": 5,
                    "name": "Matcha Latte đá",
                    "description": "",
                    "imgUrl": "https://mcdonalds.vn/uploads/2018/mccafe/xicedmatcha.png.pagespeed.ic.sUlJXqIDDo.webp",
                    "size": [
                        {
                            "sizeName": "M",
                            "price": 69000 
                        },
                        {
                            "sizeName": "L",
                            "price": 99000
                        }
                    ]
                }
            ]
        },
        {
            "categoryId": 3,
            "categoryName": "Đá xay và Yogurt",
            "item": [
                {
                    "id": 1,
                    "name": "Trà xanh đá xay",
                    "description": "",
                    "imgUrl": "https://mcdonalds.vn/uploads/2018/mccafe/xfrappematcha.png.pagespeed.ic.JbFULEvSU5.webp",
                    "size": [
                        {
                            "sizeName": "M",
                            "price": 69000 
                        },
                        {
                            "sizeName": "L",
                            "price": 89000
                        }
                    ]
                },
                {
                    "id": 2,
                    "name": "Caramen đá xay",
                    "description": "",
                    "imgUrl": "https://mcdonalds.vn/uploads/2018/mccafe/xcaramelfrappe.png.pagespeed.ic.G2cr7Q28jw.webp",
                    "size": [
                        {
                            "sizeName": "M",
                            "price": 49000 
                        },
                        {
                            "sizeName": "L",
                            "price": 79000
                        }
                    ]
                },
                {
                    "id": 3,
                    "name": "Mocha đá xay",
                    "description": "",
                    "imgUrl": "https://mcdonalds.vn/uploads/2018/mccafe/xmochafrappe.png.pagespeed.ic.Cypt_WeqFU.webp",
                    "size": [
                        {
                            "sizeName": "M",
                            "price": 55000 
                        },
                        {
                            "sizeName": "L",
                            "price": 69000
                        }
                    ]
                },
                {
                    "id": 4,
                    "name": "Latte đá xay",
                    "description": "",
                    "imgUrl": "https://mcdonalds.vn/uploads/2018/mccafe/xlattefrappe.png.pagespeed.ic.GmXWUv_xTo.webp",
                    "size": [
                        {
                            "sizeName": "M",
                            "price": 59000 
                        },
                        {
                            "sizeName": "L",
                            "price": 79000
                        }
                    ]
                },
                {
                    "id": 5,
                    "name": "Sữa chua Dâu",
                    "description": "",
                    "imgUrl": "https://mcdonalds.vn/uploads/2018/food-categories/xyogurt-dau.png.pagespeed.ic.35gPPot-p_.webp",
                    "size": [
                        {
                            "sizeName": "M",
                            "price": 59000 
                        },
                        {
                            "sizeName": "L",
                            "price": 75000
                        }
                    ]
                },
                {
                    "id": 6,
                    "name": "Sữa chua Dừa - Kiwi",
                    "description": "",
                    "imgUrl": "https://mcdonalds.vn/uploads/2018/food-categories/xyogurt-kiwi.png.pagespeed.ic.tXSyeCVuqT.webp",
                    "size": [
                        {
                            "sizeName": "M",
                            "price": 59000 
                        },
                        {
                            "sizeName": "L",
                            "price": 75000
                        }
                    ]
                }
            ]
        },
        {
            "categoryId": 4,
            "categoryName": "Kem",
            "items": [
                {
                    "id": 1,
                    "name": "Kem ốc quế",
                    "description": "",
                    "imgUrl": "https://mcdonalds.vn/uploads/2018/food/desserts/xmcdonalds_cone.png.pagespeed.ic.e59R2gJypI.webp",
                    "price": 12000
                },
                {
                    "id": 2,
                    "name": "Kem Sundae sốt Sôcôla",
                    "description": "",
                    "imgUrl": "https://mcdonalds.vn/uploads/2018/food/desserts/xhotfudge_mcsundae.png.pagespeed.ic.aZiwlX7DT-.webp",
                    "price": 29000
                },
                {
                    "id": 3,
                    "name": "Kem Sundae sốt Dâu",
                    "description": "",
                    "imgUrl": "https://mcdonalds.vn/uploads/2018/food/desserts/xstrawberry-mcsundae.png.pagespeed.ic.XQtJUMkTRF.webp",
                    "price": 29000
                },
                {
                    "id": 4,
                    "name": "Kem Xay Bánh Oreo",
                    "description": "",
                    "imgUrl": "https://mcdonalds.vn/uploads/2018/food/desserts/xoreo_mcflurry.png.pagespeed.ic.X74SrJJa1S.webp",
                    "price": 35000
                },
                {
                    "id": 5,
                    "name": "Kem Xay Bánh Oreo Trà Xanh",
                    "description": "",
                    "imgUrl": "https://mcdonalds.vn/uploads/2018/food/desserts/xmcfmc.png.pagespeed.ic.H9LOPK6FY3.webp",
                    "price": 39000
                }
            ]
        },
        {
            "categoryId": 5,
            "categoryName": "Bánh ngọt và tráng miệng",
            "items": [
                {
                    "id": 1,
                    "name": "Bánh Tiramisu",
                    "description": "",
                    "imgUrl": "https://mcdonalds.vn/uploads/2018/food-categories/xTIRAMISU.png.pagespeed.ic.3U83V4hrQ0.webp",
                    "price": 55000
                },
                {
                    "id": 2,
                    "name": "Bánh Phô mai nướng",
                    "description": "",
                    "imgUrl": "https://mcdonalds.vn/uploads/2018/food-categories/xBAKED-CHEESECAKE.png.pagespeed.ic.e5EacbrXng.webp",
                    "price": 35000
                },
                {
                    "id": 3,
                    "name": "Bánh nướng vị chuối",
                    "description": "",
                    "imgUrl": "https://mcdonalds.vn/uploads/2018/food-categories/xBANANA-MUFFIN.png.pagespeed.ic.YHoRFmbtCA.webp",
                    "price": 30000
                },
                {
                    "id": 4,
                    "name": "Bánh Brownie Sô-cô-la",
                    "description": "",
                    "imgUrl": "https://mcdonalds.vn/uploads/2018/food-categories/xCHOCO-BROWNIE.png.pagespeed.ic.Ji06bSvy4S.webp",
                    "price": 30000
                },
                {
                    "id": 5,
                    "name": "Bánh Macaron Dừa 2 cái",
                    "description": "",
                    "imgUrl": "https://mcdonalds.vn/uploads/2018/food-categories/xCOCONUT-MACAROON.png.pagespeed.ic.Hj9iPYv7j7.webp",
                    "price": 25000
                },
                {
                    "id": 6,
                    "name": "Bánh Macaron Dừa 1 cái",
                    "description": "",
                    "imgUrl": "https://mcdonalds.vn/uploads/2018/food-categories/xCSO_7425.png.pagespeed.ic.VV065-V8Uu.webp",
                    "price": 15000
                },
                {
                    "id": 7,
                    "name": "Bánh Quy Sôcôla",
                    "description": "",
                    "imgUrl": "https://mcdonalds.vn/uploads/2018/food-categories/xCHOCOLATE-CHIP-COOKIE.png.pagespeed.ic.uwWWvOPUAF.webp",
                    "price": 25000
                },
                {
                    "id": 8,
                    "name": "Bánh Sừng trâu",
                    "description": "",
                    "imgUrl": "https://mcdonalds.vn/uploads/2018/food-categories/xcroissant.png.pagespeed.ic.6zQxuJADPM.webp",
                    "price": 30000
                }
            ]
        },
        {
            "categoryId": 6,
            "categoryName": "Thức uống khác",
            "items": [
                {
                    "id": 1,
                    "name": "Trà Kem Sữa",
                    "description": "",
                    "imgUrl": "https://mcdonalds.vn/uploads/2018/food-categories/xCSO_MilkCreamTea_S.png.pagespeed.ic.2vyT1y9qjR.webp",
                    "size": [
                        {
                            "sizeName": "M",
                            "price": 59000
                        },
                        {
                            "sizeName": "L",
                            "price": 79000
                        }
                    ]
                },
                {
                    "id": 2,
                    "name": "Trà Đào",
                    "description": "",
                    "imgUrl": "https://mcdonalds.vn/uploads/2018/food-categories/xCSO_PeachTea_S.png.pagespeed.ic.ogvu68sh4b.webp",
                    "size": [
                        {
                            "sizeName": "M",
                            "price": 49000
                        },
                        {
                            "sizeName": "L",
                            "price": 65000
                        }
                    ]
                },
                {
                    "id": 3,
                    "name": "Trà Vải",
                    "description": "",
                    "imgUrl": "https://mcdonalds.vn/uploads/2018/xlychee.png.pagespeed.ic.7mFQtDeW11.webp",
                    "size": [
                        {
                            "sizeName": "M",
                            "price": 55000
                        },
                        {
                            "sizeName": "L",
                            "price": 75000
                        }
                    ]
                },
                {
                    "id": 4,
                    "name": "Tắc muối mơ ngâm hạt chia",
                    "description": "",
                    "imgUrl": "https://mcdonalds.vn/uploads/2018/mccafe/xtacmuoi.png.pagespeed.ic.fNb8M5_QFX.webp",
                    "size": [
                        {
                            "sizeName": "M",
                            "price": 40000
                        },
                        {
                            "sizeName": "L",
                            "price": 60000
                        }
                    ]
                },
                {
                    "id": 5,
                    "name": "Sữa tươi",
                    "description": "",
                    "imgUrl": "https://mcdonalds.vn/uploads/2018/food/beverage/xmilk_300x300.png.pagespeed.ic.z5vCCo0eOl.webp",
                    "price": 25000
                },
                {
                    "id": 6,
                    "name": "Fanta",
                    "description": "",
                    "imgUrl": "https://mcdonalds.vn/uploads/2018/food/beverage/xhero-pdt-Fanta-201703_0.png.pagespeed.ic.VTCOuWWJR9.webp",
                    "price": 22000
                },
                {
                    "id": 7,
                    "name": "Nước suối",
                    "description": "",
                    "imgUrl": "https://mcdonalds.vn/uploads/2018/food/beverage/xdasani_water.png.pagespeed.ic.9dIOxB9nfk.webp",
                    "price": 15000
                },
                {
                    "id": 8,
                    "name": "Sprite",
                    "description": "",
                    "imgUrl": "https://mcdonalds.vn/uploads/2018/food/beverage/xProduct_thumb_Sprite.png.pagespeed.ic.JeSrsw7hgQ.webp",
                    "price": 22000
                },
                {
                    "id": 9,
                    "name": "Coca-Cola",
                    "description": "",
                    "imgUrl": "https://mcdonalds.vn/uploads/2018/food/beverage/xmcd-food-beverages-soft-drinks-coke.png.pagespeed.ic.DnHv1b1E6D.webp",
                    "price": 22000
                }
            ]
        }
    ]
}
